textparse/__init__.py
textparse/diff.py
textparse/textparse.py
textparse/types.py
textparse-0.1.2.dist-info/METADATA
textparse-0.1.2.dist-info/WHEEL
textparse-0.1.2.dist-info/RECORD
