Metadata-Version: 2.3
Name: textparse
Version: 0.1.2
Summary: The missing text toolkit for Python
Author: Danny Stewart
Author-email: danny@stewart.cc
Requires-Python: >=3.12
Classifier: Programming Language :: Python :: 3
Classifier: Programming Language :: Python :: 3.12
Classifier: Programming Language :: Python :: 3.13
Requires-Dist: logician (>=0.3.2)
Requires-Dist: termcolor (>=3.0.1,<4.0.0)
